{
  "actores": [
    {
      "nombre": "Aceituna",
      "tipo": "Aceituna",
      "imagen": "aceituna",
      "archivo": "aceituna.ts"
    },
    {
      "nombre": "Caja",
      "tipo": "Caja",
      "imagen": "caja",
      "archivo": "caja.ts"
    },
    {
      "nombre": "Ember",
      "tipo": "ActorBasico",
      "imagen": "ember",
      "archivo": "_actor.ts"
    },
    {
      "nombre": "Logo",
      "tipo": "ActorBasico",
      "imagen": "logo",
      "archivo": "_actor.ts"
    },
    {
      "nombre": "Pelota",
      "tipo": "Pelota",
      "imagen": "pelota",
      "archivo": "_actor.ts"
    }
  ]
}
